PyStatistics/Conversions.py
PyStatistics/Factoring.py
PyStatistics/Lists.py
PyStatistics/NumberTypes.py
PyStatistics/__init__.py
idev_pystatistics-1.1.1.dist-info/LICENSE
idev_pystatistics-1.1.1.dist-info/METADATA
idev_pystatistics-1.1.1.dist-info/WHEEL
idev_pystatistics-1.1.1.dist-info/top_level.txt
idev_pystatistics-1.1.1.dist-info/RECORD
