Metadata-Version: 2.1
Name: idev-pystatistics
Version: 1.1.1
Summary: A python collection of classes and functions to help with numbers along with collections of numbers i.e., statistics.
Home-page: https://github.com/IrtsaDevelopment/PyStatistics
Author: IrtsaDevelopment
Author-email: Irtsa <irtsa.development@gmail.com>
Project-URL: Homepage, https://github.com/IrtsaDevelopment/PyStatistics
Project-URL: Bug Tracker, https://github.com/IrtsaDevelopment/PyStatistics/issues
Classifier: Programming Language :: Python :: 3
Classifier: License :: OSI Approved :: MIT License
Classifier: Operating System :: OS Independent
Requires-Python: >=3.6
License-File: LICENSE
